Metadata-Version: 2.1
Name: cn-detect
Version: 1.1.0
Summary: Recognize Chinese Name of
Home-page: https://www.linkedin.com/in/chandlersong/
Author: chandler song
Author-email: 275737875@qq.com
License: MIT
Keywords: excel chinese detector recognizer
Platform: all
Classifier: Intended Audience :: Developers
Classifier: Operating System :: OS Independent
Classifier: Natural Language :: Chinese (Simplified)
Classifier: Programming Language :: Python :: 3.7
Classifier: Programming Language :: Python :: 3.8
Classifier: Programming Language :: Python :: 3.9
Classifier: Programming Language :: Python :: 3.10
Classifier: Topic :: Software Development :: Libraries
License-File: LICENSE
